nkj/__init__.py
nkj/arg.py
nkj/cam.py
nkj/curvefit.py
nkj/cv.py
nkj/cwt.py
nkj/ea.py
nkj/fa.py
nkj/file.py
nkj/filter.py
nkj/func.py
nkj/js.py
nkj/math.py
nkj/ncore.py
nkj/np.py
nkj/os.py
nkj/plot.py
nkj/prob.py
nkj/pygame.py
nkj/serial.py
nkj/socket.py
nkj/stat.py
nkj/stats.py
nkj/str.py
nkj/test_exlist.py
nkj/time.py
nkj-1.17.dist-info/METADATA
nkj-1.17.dist-info/PKG-INFO 2
nkj-1.17.dist-info/WHEEL
nkj-1.17.dist-info/top_level.txt
nkj-1.17.dist-info/RECORD
