Metadata-Version: 2.1
Name: nkj
Version: 1.17
Summary: Surgical Navigation Kernel and Job Control Library
Author: Yoshikazu NAKAJIMA
License: bmi.tmdu
